Robei_prj/RobeiSimulation/uart_byte_tx/verilog/uart_byte_tx.v
module uart_byte_tx(
	clk,
	reset_n,
	data_byte,
	send_en,
	baud_set,
	uart_tx,
	tx_done,
	uart_state);

	//---Ports declearation: generated by Robei---
	input clk;
	input reset_n;
	input [7:0] data_byte;
	input send_en;
	input [2:0] baud_set;
	output uart_tx;
	output tx_done;
	output uart_state;

	wire clk;
	wire reset_n;
	wire [7:0] data_byte;
	wire send_en;
	wire [2:0] baud_set;
	reg uart_tx;
	reg tx_done;
	reg uart_state;

	//----Code starts here: integrated by Robei-----
		wire reset=~reset_n;
		localparam START_BIT = 1'b0;
		localparam STOP_BIT = 1'b1; 
		
		reg bps_clk;	     //波特率时钟	
		reg [15:0]div_cnt;      //分频计数器	
		reg [15:0]bps_DR;       //分频计数最大值	
		reg [3:0]bps_cnt;      //波特率时钟计数器	
		reg [7:0]data_byte_reg;//data_byte寄存后数据
		
		always@(posedge clk or posedge reset)
		if(reset)
			uart_state <= 1'b0;
		else if(send_en)
			uart_state <= 1'b1;
		else if(bps_cnt == 4'd11)
			uart_state <= 1'b0;
		else
			uart_state <= uart_state;
		
		always@(posedge clk or posedge reset)
		if(reset)
			data_byte_reg <= 8'd0;
		else if(send_en)
			data_byte_reg <= data_byte;
		else
			data_byte_reg <= data_byte_reg;
		
		always@(posedge clk or posedge reset)
		if(reset)
			bps_DR <= 16'd5207;
		else begin
			case(baud_set)
				0:bps_DR <= 16'd5207;
				1:bps_DR <= 16'd2603;
				2:bps_DR <= 16'd1301;
				3:bps_DR <= 16'd867;
				4:bps_DR <= 16'd433;
				default:bps_DR <= 16'd5207;			
			endcase
		end	
		
		//counter
		always@(posedge clk or posedge reset)
		if(reset)
			div_cnt <= 16'd0;
		else if(uart_state)begin
			if(div_cnt == bps_DR)
				div_cnt <= 16'd0;
			else
				div_cnt <= div_cnt + 1'b1;
		end
		else
			div_cnt <= 16'd0;
		
		// bps_clk gen
		always@(posedge clk or posedge reset)
		if(reset)
			bps_clk <= 1'b0;
		else if(div_cnt == 16'd1)
			bps_clk <= 1'b1;
		else
			bps_clk <= 1'b0;
		
		//bps counter
		always@(posedge clk or posedge reset)
		if(reset)	
			bps_cnt <= 4'd0;
		else if(bps_cnt == 4'd11)
			bps_cnt <= 4'd0;
		else if(bps_clk)
			bps_cnt <= bps_cnt + 1'b1;
		else
			bps_cnt <= bps_cnt;
			
		always@(posedge clk or posedge reset)
		if(reset)
			tx_done <= 1'b0;
		else if(bps_cnt == 4'd11)
			tx_done <= 1'b1;
		else
			tx_done <= 1'b0;
			
		always@(posedge clk or posedge reset)
		if(reset)
			uart_tx <= 1'b1;
		else begin
			case(bps_cnt)
				0:uart_tx <= 1'b1;
				1:uart_tx <= START_BIT;
				2:uart_tx <= data_byte_reg[0];
				3:uart_tx <= data_byte_reg[1];
				4:uart_tx <= data_byte_reg[2];
				5:uart_tx <= data_byte_reg[3];
				6:uart_tx <= data_byte_reg[4];
				7:uart_tx <= data_byte_reg[5];
				8:uart_tx <= data_byte_reg[6];
				9:uart_tx <= data_byte_reg[7];
				10:uart_tx <= STOP_BIT;
				default:uart_tx <= 1'b1;
			endcase
		end	
	
	
	
endmodule    //uart_byte_tx

Robei_prj/RobeiSimulation/uart_byte_tx/verilog/uart_byte_tx_tb.v
module uart_byte_tx_tb();

	reg clk;
	reg reset_n;
	reg [7:0] data_byte;
	reg send_en;
	reg [2:0] baud_set;
	wire uart_tx;
	wire tx_done;
	wire uart_state;

	//----Code starts here: integrated by Robei-----
			localparam CLK_PERIOD = 20;
	
		initial clk = 1;
		always#(CLK_PERIOD/2)clk = ~clk;
		
		initial begin
			reset_n = 1'b0;
			data_byte = 8'd0;
			send_en = 1'd0;
			baud_set = 3'd4;
			#(CLK_PERIOD*500 + 1 )
			reset_n = 1'b1;
			#(CLK_PERIOD*50);
	    
	    //send first byte
			data_byte = 8'haa;
			send_en = 1'd1;
			#CLK_PERIOD;
			send_en = 1'd0;
	
			@(posedge tx_done)
			#(CLK_PERIOD*5000);
	    
	    //send second byte
			data_byte = 8'h55;
			send_en = 1'd1;
			#CLK_PERIOD;
			send_en = 1'd0;
	
			@(posedge tx_done)
			#(CLK_PERIOD*5000);
			$finish;	
		end
	
	
	
	
	initial begin
		$dumpfile ("E:/CodeFile/Chusai/Simulations/uart_byte_tx/uart_byte_tx_tb.vcd");
		$dumpvars;
	end
	//---Module instantiation---
	uart_byte_tx uart_byte_tx1(
		.clk(clk),
		.reset_n(reset_n),
		.data_byte(data_byte),
		.send_en(send_en),
		.baud_set(baud_set),
		.uart_tx(uart_tx),
		.tx_done(tx_done),
		.uart_state(uart_state));

endmodule    //uart_byte_tx_tb

Robei_prj/RobeiSimulation/uart_byte_tx/uart_byte_tx_tb.vcd
$date
	Sun May 19 17:23:43 2024
$end
$version
	Icarus Verilog
$end
$timescale
	1s
$end
$scope module uart_byte_tx_tb $end
$var wire 1 ! uart_tx $end
$var wire 1 " uart_state $end
$var wire 1 # tx_done $end
$var reg 3 $ baud_set [2:0] $end
$var reg 1 % clk $end
$var reg 8 & data_byte [7:0] $end
$var reg 1 ' reset_n $end
$var reg 1 ( send_en $end
$scope module uart_byte_tx1 $end
$var wire 3 ) baud_set [2:0] $end
$var wire 1 % clk $end
$var wire 8 * data_byte [7:0] $end
$var wire 1 + reset $end
$var wire 1 ' reset_n $end
$var wire 1 ( send_en $end
$var reg 16 , bps_DR [15:0] $end
$var reg 1 - bps_clk $end
$var reg 4 . bps_cnt [3:0] $end
$var reg 8 / data_byte_reg [7:0] $end
$var reg 16 0 div_cnt [15:0] $end
$var reg 1 # tx_done $end
$var reg 1 " uart_state $end
$var reg 1 ! uart_tx $end
$upscope $end
$upscope $end
$enddefinitions $end
#0
$dumpvars
b0 0
b0 /
b0 .
0-
b1010001010111 ,
1+
b0 *
b100 )
0(
0'
b0 &
1%
b100 $
0#
0"
1!
$end
#10
0%
#20
1%
#30
0%
#40
1%
#50
0%
#60
1%
#70
0%
#80
1%
#90
0%
#100
1%
#110
0%
#120
1%
#130
0%
#140
1%
#150
0%
#160
1%
#170
0%
#180
1%
#190
0%
#200
1%
#210
0%
#220
1%
#230
0%
#240
1%
#250
0%
#260
1%
#270
0%
#280
1%
#290
0%
#300
1%
#310
0%
#320
1%
#330
0%
#340
1%
#350
0%
#360
1%
#370
0%
#380
1%
#390
0%
#400
1%
#410
0%
#420
1%
#430
0%
#440
1%
#450
0%
#460
1%
#470
0%
#480
1%
#490
0%
#500
1%
#510
0%
#520
1%
#530
0%
#540
1%
#550
0%
#560
1%
#570
0%
#580
1%
#590
0%
#600
1%
#610
0%
#620
1%
#630
0%
#640
1%
#650
0%
#660
1%
#670
0%
#680
1%
#690
0%
#700
1%
#710
0%
#720
1%
#730
0%
#740
1%
#750
0%
#760
1%
#770
0%
#780
1%
#790
0%
#800
1%
#810
0%
#820
1%
#830
0%
#840
1%
#850
0%
#860
1%
#870
0%
#880
1%
#890
0%
#900
1%
#910
0%
#920
1%
#930
0%
#940
1%
#950
0%
#960
1%
#970
0%
#980
1%
#990
0%
#1000
1%
#1010
0%
#1020
1%
#1030
0%
#1040
1%
#1050
0%
#1060
1%
#1070
0%
#1080
1%
#1090
0%
#1100
1%
#1110
0%
#1120
1%
#1130
0%
#1140
1%
#1150
0%
#1160
1%
#1170
0%
#1180
1%
#1190
0%
#1200
1%
#1210
0%
#1220
1%
#1230
0%
#1240
1%
#1250
0%
#1260
1%
#1270
0%
#1280
1%
#1290
0%
#1300
1%
#1310
0%
#1320
1%
#1330
0%
#1340
1%
#1350
0%
#1360
1%
#1370
0%
#1380
1%
#1390
0%
#1400
1%
#1410
0%
#1420
1%
#1430
0%
#1440
1%
#1450
0%
#1460
1%
#1470
0%
#1480
1%
#1490
0%
#1500
1%
#1510
0%
#1520
1%
#1530
0%
#1540
1%
#1550
0%
#1560
1%
#1570
0%
#1580
1%
#1590
0%
#1600
1%
#1610
0%
#1620
1%
#1630
0%
#1640
1%
#1650
0%
#1660
1%
#1670
0%
#1680
1%
#1690
0%
#1700
1%
#1710
0%
#1720
1%
#1730
0%
#1740
1%
#1750
0%
#1760
1%
#1770
0%
#1780
1%
#1790
0%
#1800
1%
#1810
0%
#1820
1%
#1830
0%
#1840
1%
#1850
0%
#1860
1%
#1870
0%
#1880
1%
#1890
0%
#1900
1%
#1910
0%
#1920
1%
#1930
0%
#1940
1%
#1950
0%
#1960
1%
#1970
0%
#1980
1%
#1990
0%
#2000
1%
#2010
0%
#2020
1%
#2030
0%
#2040
1%
#2050
0%
#2060
1%
#2070
0%
#2080
1%
#2090
0%
#2100
1%
#2110
0%
#2120
1%
#2130
0%
#2140
1%
#2150
0%
#2160
1%
#2170
0%
#2180
1%
#2190
0%
#2200
1%
#2210
0%
#2220
1%
#2230
0%
#2240
1%
#2250
0%
#2260
1%
#2270
0%
#2280
1%
#2290
0%
#2300
1%
#2310
0%
#2320
1%
#2330
0%
#2340
1%
#2350
0%
#2360
1%
#2370
0%
#2380
1%
#2390
0%
#2400
1%
#2410
0%
#2420
1%
#2430
0%
#2440
1%
#2450
0%
#2460
1%
#2470
0%
#2480
1%
#2490
0%
#2500
1%
#2510
0%
#2520
1%
#2530
0%
#2540
1%
#2550
0%
#2560
1%
#2570
0%
#2580
1%
#2590
0%
#2600
1%
#2610
0%
#2620
1%
#2630
0%
#2640
1%
#2650
0%
#2660
1%
#2670
0%
#2680
1%
#2690
0%
#2700
1%
#2710
0%
#2720
1%
#2730
0%
#2740
1%
#2750
0%
#2760
1%
#2770
0%
#2780
1%
#2790
0%
#2800
1%
#2810
0%
#2820
1%
#2830
0%
#2840
1%
#2850
0%
#2860
1%
#2870
0%
#2880
1%
#2890
0%
#2900
1%
#2910
0%
#2920
1%
#2930
0%
#2940
1%
#2950
0%
#2960
1%
#2970
0%
#2980
1%
#2990
0%
#3000
1%
#3010
0%
#3020
1%
#3030
0%
#3040
1%
#3050
0%
#3060
1%
#3070
0%
#3080
1%
#3090
0%
#3100
1%
#3110
0%
#3120
1%
#3130
0%
#3140
1%
#3150
0%
#3160
1%
#3170
0%
#3180
1%
#3190
0%
#3200
1%
#3210
0%
#3220
1%
#3230
0%
#3240
1%
#3250
0%
#3260
1%
#3270
0%
#3280
1%
#3290
0%
#3300
1%
#3310
0%
#3320
1%
#3330
0%
#3340
1%
#3350
0%
#3360
1%
#3370
0%
#3380
1%
#3390
0%
#3400
1%
#3410
0%
#3420
1%
#3430
0%
#3440
1%
#3450
0%
#3460
1%
#3470
0%
#3480
1%
#3490
0%
#3500
1%
#3510
0%
#3520
1%
#3530
0%
#3540
1%
#3550
0%
#3560
1%
#3570
0%
#3580
1%
#3590
0%
#3600
1%
#3610
0%
#3620
1%
#3630
0%
#3640
1%
#3650
0%
#3660
1%
#3670
0%
#3680
1%
#3690
0%
#3700
1%
#3710
0%
#3720
1%
#3730
0%
#3740
1%
#3750
0%
#3760
1%
#3770
0%
#3780
1%
#3790
0%
#3800
1%
#3810
0%
#3820
1%
#3830
0%
#3840
1%
#3850
0%
#3860
1%
#3870
0%
#3880
1%
#3890
0%
#3900
1%
#3910
0%
#3920
1%
#3930
0%
#3940
1%
#3950
0%
#3960
1%
#3970
0%
#3980
1%
#3990
0%
#4000
1%
#4010
0%
#4020
1%
#4030
0%
#4040
1%
#4050
0%
#4060
1%
#4070
0%
#4080
1%
#4090
0%
#4100
1%
#4110
0%
#4120
1%
#4130
0%
#4140
1%
#4150
0%
#4160
1%
#4170
0%
#4180
1%
#4190
0%
#4200
1%
#4210
0%
#4220
1%
#4230
0%
#4240
1%
#4250
0%
#4260
1%
#4270
0%
#4280
1%
#4290
0%
#4300
1%
#4310
0%
#4320
1%
#4330
0%
#4340
1%
#4350
0%
#4360
1%
#4370
0%
#4380
1%
#4390
0%
#4400
1%
#4410
0%
#4420
1%
#4430
0%
#4440
1%
#4450
0%
#4460
1%
#4470
0%
#4480
1%
#4490
0%
#4500
1%
#4510
0%
#4520
1%
#4530
0%
#4540
1%
#4550
0%
#4560
1%
#4570
0%
#4580
1%
#4590
0%
#4600
1%
#4610
0%
#4620
1%
#4630
0%
#4640
1%
#4650
0%
#4660
1%
#4670
0%
#4680
1%
#4690
0%
#4700
1%
#4710
0%
#4720
1%
#4730
0%
#4740
1%
#4750
0%
#4760
1%
#4770
0%
#4780
1%
#4790
0%
#4800
1%
#4810
0%
#4820
1%
#4830
0%
#4840
1%
#4850
0%
#4860
1%
#4870
0%
#4880
1%
#4890
0%
#4900
1%
#4910
0%
#4920
1%
#4930
0%
#4940
1%
#4950
0%
#4960
1%
#4970
0%
#4980
1%
#4990
0%
#5000
1%
#5010
0%
#5020
1%
#5030
0%
#5040
1%
#5050
0%
#5060
1%
#5070
0%
#5080
1%
#5090
0%
#5100
1%
#5110
0%
#5120
1%
#5130
0%
#5140
1%
#5150
0%
#5160
1%
#5170
0%
#5180
1%
#5190
0%
#5200
1%
#5210
0%
#5220
1%
#5230
0%
#5240
1%
#5250
0%
#5260
1%
#5270
0%
#5280
1%
#5290
0%
#5300
1%
#5310
0%
#5320
1%
#5330
0%
#5340
1%
#5350
0%
#5360
1%
#5370
0%
#5380
1%
#5390
0%
#5400
1%
#5410
0%
#5420
1%
#5430
0%
#5440
1%
#5450
0%
#5460
1%
#5470
0%
#5480
1%
#5490
0%
#5500
1%
#5510
0%
#5520
1%
#5530
0%
#5540
1%
#5550
0%
#5560
1%
#5570
0%
#5580
1%
#5590
0%
#5600
1%
#5610
0%
#5620
1%
#5630
0%
#5640
1%
#5650
0%
#5660
1%
#5670
0%
#5680
1%
#5690
0%
#5700
1%
#5710
0%
#5720
1%
#5730
0%
#5740
1%
#5750
0%
#5760
1%
#5770
0%
#5780
1%
#5790
0%
#5800
1%
#5810
0%
#5820
1%
#5830
0%
#5840
1%
#5850
0%
#5860
1%
#5870
0%
#5880
1%
#5890
0%
#5900
1%
#5910
0%
#5920
1%
#5930
0%
#5940
1%
#5950
0%
#5960
1%
#5970
0%
#5980
1%
#5990
0%
#6000
1%
#6010
0%
#6020
1%
#6030
0%
#6040
1%
#6050
0%
#6060
1%
#6070
0%
#6080
1%
#6090
0%
#6100
1%
#6110
0%
#6120
1%
#6130
0%
#6140
1%
#6150
0%
#6160
1%
#6170
0%
#6180
1%
#6190
0%
#6200
1%
#6210
0%
#6220
1%
#6230
0%
#6240
1%
#6250
0%
#6260
1%
#6270
0%
#6280
1%
#6290
0%
#6300
1%
#6310
0%
#6320
1%
#6330
0%
#6340
1%
#6350
0%
#6360
1%
#6370
0%
#6380
1%
#6390
0%
#6400
1%
#6410
0%
#6420
1%
#6430
0%
#6440
1%
#6450
0%
#6460
1%
#6470
0%
#6480
1%
#6490
0%
#6500
1%
#6510
0%
#6520
1%
#6530
0%
#6540
1%
#6550
0%
#6560
1%
#6570
0%
#6580
1%
#6590
0%
#6600
1%
#6610
0%
#6620
1%
#6630
0%
#6640
1%
#6650
0%
#6660
1%
#6670
0%
#6680
1%
#6690
0%
#6700
1%
#6710
0%
#6720
1%
#6730
0%
#6740
1%
#6750
0%
#6760
1%
#6770
0%
#6780
1%
#6790
0%
#6800
1%
#6810
0%
#6820
1%
#6830
0%
#6840
1%
#6850
0%
#6860
1%
#6870
0%
#6880
1%
#6890
0%
#6900
1%
#6910
0%
#6920
1%
#6930
0%
#6940
1%
#6950
0%
#6960
1%
#6970
0%
#6980
1%
#6990
0%
#7000
1%
#7010
0%
#7020
1%
#7030
0%
#7040
1%
#7050
0%
#7060
1%
#7070
0%
#7080
1%
#7090
0%
#7100
1%
#7110
0%
#7120
1%
#7130
0%
#7140
1%
#7150
0%
#7160
1%
#7170
0%
#7180
1%
#7190
0%
#7200
1%
#7210
0%
#7220
1%
#7230
0%
#7240
1%
#7250
0%
#7260
1%
#7270
0%
#7280
1%
#7290
0%
#7300
1%
#7310
0%
#7320
1%
#7330
0%
#7340
1%
#7350
0%
#7360
1%
#7370
0%
#7380
1%
#7390
0%
#7400
1%
#7410
0%
#7420
1%
#7430
0%
#7440
1%
#7450
0%
#7460
1%
#7470
0%
#7480
1%
#7490
0%
#7500
1%
#7510
0%
#7520
1%
#7530
0%
#7540
1%
#7550
0%
#7560
1%
#7570
0%
#7580
1%
#7590
0%
#7600
1%
#7610
0%
#7620
1%
#7630
0%
#7640
1%
#7650
0%
#7660
1%
#7670
0%
#7680
1%
#7690
0%
#7700
1%
#7710
0%
#7720
1%
#7730
0%
#7740
1%
#7750
0%
#7760
1%
#7770
0%
#7780
1%
#7790
0%
#7800
1%
#7810
0%
#7820
1%
#7830
0%
#7840
1%
#7850
0%
#7860
1%
#7870
0%
#7880
1%
#7890
0%
#7900
1%
#7910
0%
#7920
1%
#7930
0%
#7940
1%
#7950
0%
#7960
1%
#7970
0%
#7980
1%
#7990
0%
#8000
1%
#8010
0%
#8020
1%
#8030
0%
#8040
1%
#8050
0%
#8060
1%
#8070
0%
#8080
1%
#8090
0%
#8100
1%
#8110
0%
#8120
1%
#8130
0%
#8140
1%
#8150
0%
#8160
1%
#8170
0%
#8180
1%
#8190
0%
#8200
1%
#8210
0%
#8220
1%
#8230
0%
#8240
1%
#8250
0%
#8260
1%
#8270
0%
#8280
1%
#8290
0%
#8300
1%
#8310
0%
#8320
1%
#8330
0%
#8340
1%
#8350
0%
#8360
1%
#8370
0%
#8380
1%
#8390
0%
#8400
1%
#8410
0%
#8420
1%
#8430
0%
#8440
1%
#8450
0%
#8460
1%
#8470
0%
#8480
1%
#8490
0%
#8500
1%
#8510
0%
#8520
1%
#8530
0%
#8540
1%
#8550
0%
#8560
1%
#8570
0%
#8580
1%
#8590
0%
#8600
1%
#8610
0%
#8620
1%
#8630
0%
#8640
1%
#8650
0%
#8660
1%
#8670
0%
#8680
1%
#8690
0%
#8700
1%
#8710
0%
#8720
1%
#8730
0%
#8740
1%
#8750
0%
#8760
1%
#8770
0%
#8780
1%
#8790
0%
#8800
1%
#8810
0%
#8820
1%
#8830
0%
#8840
1%
#8850
0%
#8860
1%
#8870
0%
#8880
1%
#8890
0%
#8900
1%
#8910
0%
#8920
1%
#8930
0%
#8940
1%
#8950
0%
#8960
1%
#8970
0%
#8980
1%
#8990
0%
#9000
1%
#9010
0%
#9020
1%
#9030
0%
#9040
1%
#9050
0%
#9060
1%
#9070
0%
#9080
1%
#9090
0%
#9100
1%
#9110
0%
#9120
1%
#9130
0%
#9140
1%
#9150
0%
#9160
1%
#9170
0%
#9180
1%
#9190
0%
#9200
1%
#9210
0%
#9220
1%
#9230
0%
#9240
1%
#9250
0%
#9260
1%
#9270
0%
#9280
1%
#9290
0%
#9300
1%
#9310
0%
#9320
1%
#9330
0%
#9340
1%
#9350
0%
#9360
1%
#9370
0%
#9380
1%
#9390
0%
#9400
1%
#9410
0%
#9420
1%
#9430
0%
#9440
1%
#9450
0%
#9460
1%
#9470
0%
#9480
1%
#9490
0%
#9500
1%
#9510
0%
#9520
1%
#9530
0%
#9540
1%
#9550
0%
#9560
1%
#9570
0%
#9580
1%
#9590
0%
#9600
1%
#9610
0%
#9620
1%
#9630
0%
#9640
1%
#9650
0%
#9660
1%
#9670
0%
#9680
1%
#9690
0%
#9700
1%
#9710
0%
#9720
1%
#9730
0%
#9740
1%
#9750
0%
#9760
1%
#9770
0%
#9780
1%
#9790
0%
#9800
1%
#9810
0%
#9820
1%
#9830
0%
#9840
1%
#9850
0%
#9860
1%
#9870
0%
#9880
1%
#9890
0%
#9900
1%
#9910
0%
#9920
1%
#9930
0%
#9940
1%
#9950
0%
#9960
1%
#9970
0%
#9980
1%
#9990
0%
#10000
1%
#10001
0+
1'
#10010
0%
#10020
b110110001 ,
1%
#10030
0%
#10040
1%
#10050
0%
#10060
1%
#10070
0%
#10080
1%
#10090
0%
#10100
1%
#10110
0%
#10120
1%
#10130
0%
#10140
1%
#10150
0%
#10160
1%
#10170
0%
#10180
1%
#10190
0%
#10200
1%
#10210
0%
#10220
1%
#10230
0%
#10240
1%
#10250
0%
#10260
1%
#10270
0%
#10280
1%
#10290
0%
#10300
1%
#10310
0%
#10320
1%
#10330
0%
#10340
1%
#10350
0%
#10360
1%
#10370
0%
#10380
1%
#10390
0%
#10400
1%
#10410
0%
#10420
1%
#10430
0%
#10440
1%
#10450
0%
#10460
1%
#10470
0%
#10480
1%
#10490
0%
#10500
1%
#10510
0%
#10520
1%
#10530
0%
#10540
1%
#10550
0%
#10560
1%
#10570
0%
#10580
1%
#10590
0%
#10600
1%
#10610
0%
#10620
1%
#10630
0%
#10640
1%
#10650
0%
#10660
1%
#10670
0%
#10680
1%
#10690
0%
#10700
1%
#10710
0%
#10720
1%
#10730
0%
#10740
1%
#10750
0%
#10760
1%
#10770
0%
#10780
1%
#10790
0%
#10800
1%
#10810
0%
#10820
1%
#10830
0%
#10840
1%
#10850
0%
#10860
1%
#10870
0%
#10880
1%
#10890
0%
#10900
1%
#10910
0%
#10920
1%
#10930
0%
#10940
1%
#10950
0%
#10960
1%
#10970
0%
#10980
1%
#10990
0%
#11000
1%
#11001
1(
b10101010 &
b10101010 *
#11010
0%
#11020
1"
b10101010 /
1%
#11021
0(
#11030
0%
#11040
b1 0
1%
#11050
0%
#11060
b10 0
1-
1%
#11070
0%
#11080
b1 .
0-
b11 0
1%
#11090
0%
#11100
b100 0
0!
1%
#11110
0%
#11120
b101 0
1%
#11130
0%
#11140
b110 0
1%
#11150
0%
#11160
b111 0
1%
#11170
0%
#11180
b1000 0
1%
#11190
0%
#11200
b1001 0
1%
#11210
0%
#11220
b1010 0
1%
#11230
0%
#11240
b1011 0
1%
#11250
0%
#11260
b1100 0
1%
#11270
0%
#11280
b1101 0
1%
#11290
0%
#11300
b1110 0
1%
#11310
0%
#11320
b1111 0
1%
#11330
0%
#11340
b10000 0
1%
#11350
0%
#11360
b10001 0
1%
#11370
0%
#11380
b10010 0
1%
#11390
0%
#11400
b10011 0
1%
#11410
0%
#11420
b10100 0
1%
#11430
0%
#11440
b10101 0
1%
#11450
0%
#11460
b10110 0
1%
#11470
0%
#11480
b10111 0
1%
#11490
0%
#11500
b11000 0
1%
#11510
0%
#11520
b11001 0
1%
#11530
0%
#11540
b11010 0
1%
#11550
0%
#11560
b11011 0
1%
#11570
0%
#11580
b11100 0
1%
#11590
0%
#11600
b11101 0
1%
#11610
0%
#11620
b11110 0
1%
#11630
0%
#11640
b11111 0
1%
#11650
0%
#11660
b100000 0
1%
#11670
0%
#11680
b100001 0
1%
#11690
0%
#11700
b100010 0
1%
#11710
0%
#11720
b100011 0
1%
#11730
0%
#11740
b100100 0
1%
#11750
0%
#11760
b100101 0
1%
#11770
0%
#11780
b100110 0
1%
#11790
0%
#11800
b100111 0
1%
#11810
0%
#11820
b101000 0
1%
#11830
0%
#11840
b101001 0
1%
#11850
0%
#11860
b101010 0
1%
#11870
0%
#11880
b101011 0
1%
#11890
0%
#11900
b101100 0
1%
#11910
0%
#11920
b101101 0
1%
#11930
0%
#11940
b101110 0
1%
#11950
0%
#11960
b101111 0
1%
#11970
0%
#11980
b110000 0
1%
#11990
0%
#12000
b110001 0
1%
#12010
0%
#12020
b110010 0
1%
#12030
0%
#12040
b110011 0
1%
#12050
0%
#12060
b110100 0
1%
#12070
0%
#12080
b110101 0
1%
#12090
0%
#12100
b110110 0
1%
#12110
0%
#12120
b110111 0
1%
#12130
0%
#12140
b111000 0
1%
#12150
0%
#12160
b111001 0
1%
#12170
0%
#12180
b111010 0
1%
#12190
0%
#12200
b111011 0
1%
#12210
0%
#12220
b111100 0
1%
#12230
0%
#12240
b111101 0
1%
#12250
0%
#12260
b111110 0
1%
#12270
0%
#12280
b111111 0
1%
#12290
0%
#12300
b1000000 0
1%
#12310
0%
#12320
b1000001 0
1%
#12330
0%
#12340
b1000010 0
1%
#12350
0%
#12360
b1000011 0
1%
#12370
0%
#12380
b1000100 0
1%
#12390
0%
#12400
b1000101 0
1%
#12410
0%
#12420
b1000110 0
1%
#12430
0%
#12440
b1000111 0
1%
#12450
0%
#12460
b1001000 0
1%
#12470
0%
#12480
b1001001 0
1%
#12490
0%
#12500
b1001010 0
1%
#12510
0%
#12520
b1001011 0
1%
#12530
0%
#12540
b1001100 0
1%
#12550
0%
#12560
b1001101 0
1%
#12570
0%
#12580
b1001110 0
1%
#12590
0%
#12600
b1001111 0
1%
#12610
0%
#12620
b1010000 0
1%
#12630
0%
#12640
b1010001 0
1%
#12650
0%
#12660
b1010010 0
1%
#12670
0%
#12680
b1010011 0
1%
#12690
0%
#12700
b1010100 0
1%
#12710
0%
#12720
b1010101 0
1%
#12730
0%
#12740
b1010110 0
1%
#12750
0%
#12760
b1010111 0
1%
#12770
0%
#12780
b1011000 0
1%
#12790
0%
#12800
b1011001 0
1%
#12810
0%
#12820
b1011010 0
1%
#12830
0%
#12840
b1011011 0
1%
#12850
0%
#12860
b1011100 0
1%
#12870
0%
#12880
b1011101 0
1%
#12890
0%
#12900
b1011110 0
1%
#12910
0%
#12920
b1011111 0
1%
#12930
0%
#12940
b1100000 0
1%
#12950
0%
#12960
b1100001 0
1%
#12970
0%
#12980
b1100010 0
1%
#12990
0%
#13000
b1100011 0
1%
#13010
0%
#13020
b1100100 0
1%
#13030
0%
#13040
b1100101 0
1%
#13050
0%
#13060
b1100110 0
1%
#13070
0%
#13080
b1100111 0
1%
#13090
0%
#13100
b1101000 0
1%
#13110
0%
#13120
b1101001 0
1%
#13130
0%
#13140
b1101010 0
1%
#13150
0%
#13160
b1101011 0
1%
#13170
0%
#13180
b1101100 0
1%
#13190
0%
#13200
b1101101 0
1%
#13210
0%
#13220
b1101110 0
1%
#13230
0%
#13240
b1101111 0
1%
#13250
0%
#13260
b1110000 0
1%
#13270
0%
#13280
b1110001 0
1%
#13290
0%
#13300
b1110010 0
1%
#13310
0%
#13320
b1110011 0
1%
#13330
0%
#13340
b1110100 0
1%
#13350
0%
#13360
b1110101 0
1%
#13370
0%
#13380
b1110110 0
1%
#13390
0%
#13400
b1110111 0
1%
#13410
0%
#13420
b1111000 0
1%
#13430
0%
#13440
b1111001 0
1%
#13450
0%
#13460
b1111010 0
1%
#13470
0%
#13480
b1111011 0
1%
#13490
0%
#13500
b1111100 0
1%
#13510
0%
#13520
b1111101 0
1%
#13530
0%
#13540
b1111110 0
1%
#13550
0%
#13560
b1111111 0
1%
#13570
0%
#13580
b10000000 0
1%
#13590
0%
#13600
b10000001 0
1%
#13610
0%
#13620
b10000010 0
1%
#13630
0%
#13640
b10000011 0
1%
#13650
0%
#13660
b10000100 0
1%
#13670
0%
#13680
b10000101 0
1%
#13690
0%
#13700
b10000110 0
1%
#13710
0%
#13720
b10000111 0
1%
#13730
0%
#13740
b10001000 0
1%
#13750
0%
#13760
b10001001 0
1%
#13770
0%
#13780
b10001010 0
1%
#13790
0%
#13800
b10001011 0
1%
#13810
0%
#13820
b10001100 0
1%
#13830
0%
#13840
b10001101 0
1%
#13850
0%
#13860
b10001110 0
1%
#13870
0%
#13880
b10001111 0
1%
#13890
0%
#13900
b10010000 0
1%
#13910
0%
#13920
b10010001 0
1%
#13930
0%
#13940
b10010010 0
1%
#13950
0%
#13960
b10010011 0
1%
#13970
0%
#13980
b10010100 0
1%
#13990
0%
#14000
b10010101 0
1%
#14010
0%
#14020
b10010110 0
1%
#14030
0%
#14040
b10010111 0
1%
#14050
0%
#14060
b10011000 0
1%
#14070
0%
#14080
b10011001 0
1%
#14090
0%
#14100
b10011010 0
1%
#14110
0%
#14120
b10011011 0
1%
#14130
0%
#14140
b10011100 0
1%
#14150
0%
#14160
b10011101 0
1%
#14170
0%
#14180
b10011110 0
1%
#14190
0%
#14200
b10011111 0
1%
#14210
0%
#14220
b10100000 0
1%
#14230
0%
#14240
b10100001 0
1%
#14250
0%
#14260
b10100010 0
1%
#14270
0%
#14280
b10100011 0
1%
#14290
0%
#14300
b10100100 0
1%
#14310
0%
#14320
b10100101 0
1%
#14330
0%
#14340
b10100110 0
1%
#14350
0%
#14360
b10100111 0
1%
#14370
0%
#14380
b10101000 0
1%
#14390
0%
#14400
b10101001 0
1%
#14410
0%
#14420
b10101010 0
1%
#14430
0%
#14440
b10101011 0
1%
#14450
0%
#14460
b10101100 0
1%
#14470
0%
#14480
b10101101 0
1%
#14490
0%
#14500
b10101110 0
1%
#14510
0%
#14520
b10101111 0
1%
#14530
0%
#14540
b10110000 0
1%
#14550
0%
#14560
b10110001 0
1%
#14570
0%
#14580
b10110010 0
1%
#14590
0%
#14600
b10110011 0
1%
#14610
0%
#14620
b10110100 0
1%
#14630
0%
#14640
b10110101 0
1%
#14650
0%
#14660
b10110110 0
1%
#14670
0%
#14680
b10110111 0
1%
#14690
0%
#14700
b10111000 0
1%
#14710
0%
#14720
b10111001 0
1%
#14730
0%
#14740
b10111010 0
1%
#14750
0%
#14760
b10111011 0
1%
#14770
0%
#14780
b10111100 0
1%
#14790
0%
#14800
b10111101 0
1%
#14810
0%
#14820
b10111110 0
1%
#14830
0%
#14840
b10111111 0
1%
#14850
0%
#14860
b11000000 0
1%
#14870
0%
#14880
b11000001 0
1%
#14890
0%
#14900
b11000010 0
1%
#14910
0%
#14920
b11000011 0
1%
#14930
0%
#14940
b11000100 0
1%
#14950
0%
#14960
b11000101 0
1%
#14970
0%
#14980
b11000110 0
1%
#14990
0%
#15000
b11000111 0
1%
#15010
0%
#15020
b11001000 0
1%
#15030
0%
#15040
b11001001 0
1%
#15050
0%
#15060
b11001010 0
1%
#15070
0%
#15080
b11001011 0
1%
#15090
0%
#15100
b11001100 0
1%
#15110
0%
#15120
b11001101 0
1%
#15130
0%
#15140
b11001110 0
1%
#15150
0%
#15160
b11001111 0
1%
#15170
0%
#15180
b11010000 0
1%
#15190
0%
#15200
b11010001 0
1%
#15210
0%
