Robei_prj/RobeiSimulation/LCD_single_ROM2/verilog/single_ROM2.v
module single_ROM2(
	clk,
	addr,
	q);

	//---Ports declearation: generated by Robei---
	input clk;
	input [18:0] addr;
	output [7:0] q;

	wire clk;
	wire [18:0] addr;
	reg [7:0] q;

	//----Code starts here: integrated by Robei-----
		parameter DATA_WIDTH = 8;
		parameter ADDR_DEPTH = 500000;
		
		    parameter   DELAY   = 1     ;//read data output delay
		
		reg [DATA_WIDTH-1:0] rom[ADDR_DEPTH-1:0];			//			2**ADDR_WIDTH=2^(ADDR_WIDTH)
		
		initial 
		begin
		    $readmemh("E:/CodeFile/Fusai/BAJIAOBAN/Top_Final/vivado/Picture_Data/output2.txt", rom);   //读取16进制数据
																							//读取2进制数据
		end
		
		reg [DATA_WIDTH-1:0] buffer [0:DELAY];
		
		always @(posedge clk)
		    begin
		
		 //读操作条件，当RDEnable为1且CS为1时，将Addr指定的内存单元中的数据读出并暂存在Data_read中
		   q <= rom[addr];
		 //其他条件，当CS为0或RDEnable为不确定值时，将Data_read置为高阻抗状态
		    end
		
		
		always@(posedge clk) begin
		
		        buffer[1] <= buffer[0];
		
		end
		
		//assign q = buffer[0];
endmodule    //single_ROM2

Robei_prj/RobeiSimulation/LCD_single_ROM2/verilog/single_ROM_tb2.v
module single_ROM_tb();

	reg clk;
	reg [ADDR_WIDTH ] addr;
	wire [DATA_WIDTH ] q;

	//----Code starts here: integrated by Robei-----
	parameter DATA_WIDTH = 8;
	parameter ADDR_WIDTH = 19;
	
	initial
	begin
	clk=0;
	addr<=0;
	
	
	
	#100;
	$finish;
	end
	
	always @(posedge clk) begin
	
			addr <= addr + 1'b1;
	
	end
	
	
	always #1 clk=~clk;    //时钟周期为2ns
	
	//ROM ROM_test(.addr(addr),.clk(clk),.q(q) );
	
	//ROM ROM_test(.rst(rst),.clk(clk),.o_sine(o_sine),.o_squ(o_squ),.o_tri(o_tri) );
	
	
	
	
	
	
	initial begin
		$dumpfile ("E:/CodeFile/Fusai/BAJIAOBAN/Top_Final/RobeiSimulation/single_ROM2/single_ROM_tb.vcd");
		$dumpvars;
	end
	//---Module instantiation---
	single_ROM2 single_ROM21(
		.clk(clk),
		.addr(addr),
		.q(q));

endmodule    //single_ROM_tb

Robei_prj/RobeiSimulation/LCD_single_ROM2/single_ROM_tb.vcd
$date
	Sat Jul 06 01:42:04 2024
$end
$version
	Icarus Verilog
$end
$timescale
	1s
$end
$scope module single_ROM_tb $end
$var wire 8 ! q [0:7] $end
$var reg 19 " addr [0:18] $end
$var reg 1 # clk $end
$scope module single_ROM21 $end
$var wire 19 $ addr [18:0] $end
$var wire 1 # clk $end
$var reg 8 % q [7:0] $end
$upscope $end
$upscope $end
$enddefinitions $end
#0
$dumpvars
bx %
b0 $
0#
b0 "
bx !
$end
#1
b11111111 !
b11111111 %
b1 "
b1 $
1#
#2
0#
#3
b10 "
b10 $
1#
#4
0#
#5
b11 "
b11 $
1#
#6
0#
#7
b100 "
b100 $
1#
#8
0#
#9
b101 "
b101 $
1#
#10
0#
#11
b110 "
b110 $
1#
#12
0#
#13
b111 "
b111 $
1#
#14
0#
#15
b1000 "
b1000 $
1#
#16
0#
#17
b1001 "
b1001 $
1#
#18
0#
#19
b1010 "
b1010 $
1#
#20
0#
#21
b1011 "
b1011 $
1#
#22
0#
#23
b1100 "
b1100 $
1#
#24
0#
#25
b1101 "
b1101 $
1#
#26
0#
#27
b1110 "
b1110 $
1#
#28
0#
#29
b1111 "
b1111 $
1#
#30
0#
#31
b10000 "
b10000 $
1#
#32
0#
#33
b10001 "
b10001 $
1#
#34
0#
#35
b10010 "
b10010 $
1#
#36
0#
#37
b10011 "
b10011 $
1#
#38
0#
#39
b10100 "
b10100 $
1#
#40
0#
#41
b10101 "
b10101 $
1#
#42
0#
#43
b10110 "
b10110 $
1#
#44
0#
#45
b10111 "
b10111 $
1#
#46
0#
#47
b11000 "
b11000 $
1#
#48
0#
#49
b11001 "
b11001 $
1#
#50
0#
#51
b11010 "
b11010 $
1#
#52
0#
#53
b11011 "
b11011 $
1#
#54
0#
#55
b11100 "
b11100 $
1#
#56
0#
#57
b11101 "
b11101 $
1#
#58
0#
#59
b11110 "
b11110 $
1#
#60
0#
#61
b11111 "
b11111 $
1#
#62
0#
#63
b100000 "
b100000 $
1#
#64
0#
#65
b100001 "
b100001 $
1#
#66
0#
#67
b100010 "
b100010 $
1#
#68
0#
#69
b100011 "
b100011 $
1#
#70
0#
#71
b100100 "
b100100 $
1#
#72
0#
#73
b100101 "
b100101 $
1#
#74
0#
#75
b100110 "
b100110 $
1#
#76
0#
#77
b100111 "
b100111 $
1#
#78
0#
#79
b101000 "
b101000 $
1#
#80
0#
#81
b101001 "
b101001 $
1#
#82
0#
#83
b101010 "
b101010 $
1#
#84
0#
#85
b101011 "
b101011 $
1#
#86
0#
#87
b101100 "
b101100 $
1#
#88
0#
#89
b101101 "
b101101 $
1#
#90
0#
#91
b101110 "
b101110 $
1#
#92
0#
#93
b101111 "
b101111 $
1#
#94
0#
#95
b110000 "
b110000 $
1#
#96
0#
#97
b110001 "
b110001 $
1#
#98
0#
#99
b110010 "
b110010 $
1#
