Robei_prj/RobeiSimulation/Top/verilog/arm_cal_m.v
module arm_cal_m(
	Clk,
	Rst_n,
	input_cmd,
	data_out,
	send_en_out,
	input_id,
	Tx_Done_flag);

	//---Ports declearation: generated by Robei---
	input Clk;
	input Rst_n;
	input input_cmd;
	output [79:0] data_out;
	output send_en_out;
	input [7:0] input_id;
	input Tx_Done_flag;

	wire Clk;
	wire Rst_n;
	wire input_cmd;
	reg [79:0] data_out;
	reg send_en_out;
	wire [7:0] input_id;
	wire Tx_Done_flag;

	//----Code starts here: integrated by Robei-----
			parameter DATA_WIDTH = 80;
			parameter fill_data = 8'h55;//55
			parameter delta_angle_low = 8'h1a;//每次变化角度5°对1来说太大了1应该就
			parameter delta_angle_heigh = 8'h00;
			parameter time_low = 8'hf4;//f4 
			parameter time_heigh =8'h00; //01
			reg [DATA_WIDTH-1:0] reg_out_data;
			reg [7:0] angle_low [5:0];
			reg [7:0] angle_heigh [5:0];
			reg [7:0] reg_cal;////////////////
			reg [7:0] med_angle;
			reg [7:0] in_low;
			reg [7:0] in_heigh;
			reg [7:0] reg_id;
			reg [7:0] send_id;
			reg run_valid;
			integer i;
			
			localparam S0 = 0;	//等待发送请求
			localparam S1 = 1;	//计算数据发送
			localparam S2 = 2;	//等待单字节数据发送完成
			localparam S3 = 3;	//检查所有数据是否发送完成
			reg [2:0] Rst_length;
			reg [1:0] state_cal;
			always @(posedge Clk or negedge Rst_n)
			begin
			if (!Rst_n)
				begin
				angle_low[0] <= 8'hE9;
				angle_heigh[0] <= 8'h00;
				angle_low[1] <= 8'hFA;
				angle_heigh[1] <= 8'h01;
				angle_low[2] <= 8'h92;
				angle_heigh[2] <= 8'h00;
				angle_low[3] <= 8'h6a;
				angle_heigh[3] <= 8'h03;
				angle_low[4] <= 8'h08;
				angle_heigh[4] <= 8'h02;
				angle_low[5] <= 8'hF4;
				angle_heigh[5] <= 8'h01;
				med_angle <= 8'h0;
				in_low <= 8'h0;
				in_heigh <= 8'h0;
				reg_id <= 8'h0;
				send_id <= 8'h0;
				state_cal <= S0;
				reg_cal <= 8'h0;
				Rst_length <= 3'h2;
				end
			else
				begin
					//计算数据
				case(state_cal)
				S0:
					begin
					if(input_id != 8'h0)
						begin
		                Rst_length <= 3'h2;
						state_cal <= S1;
						reg_id <= input_id;
						end
					end
				S1:
					begin
					case(reg_id)
						8'h1:
							begin
							in_low = angle_low[0];
							in_heigh = angle_heigh[0]; 
							if (input_cmd)  //加法 ??????????阻塞or非阻塞,顺时针
								add_model(in_low,in_heigh,angle_low[0],angle_heigh[0]);
							else 
								sub_model(in_low,in_heigh,angle_low[0],angle_heigh[0]);
							in_low <= angle_low[0];
							in_heigh <= angle_heigh[0]; 
							send_id <= reg_id;
							end
						8'h2:
							begin
							in_low = angle_low[1];
							in_heigh = angle_heigh[1]; 
							if (input_cmd) 
								add_model(in_low,in_heigh,angle_low[1],angle_heigh[1]);
							else 
								sub_model(in_low,in_heigh,angle_low[1],angle_heigh[1]);
							in_low <= angle_low[1];
							in_heigh <= angle_heigh[1]; 
							send_id <= reg_id;
							end
						8'h3:
							begin
							in_low = angle_low[2];
							in_heigh = angle_heigh[2]; 
							if (input_cmd)
								add_model(in_low,in_heigh,angle_low[2],angle_heigh[2]);
							else 
								sub_model(in_low,in_heigh,angle_low[2],angle_heigh[2]);
							in_low <= angle_low[2];
							in_heigh <= angle_heigh[2];
							send_id <= reg_id; 
							end
						8'h4:
							begin
							in_low = angle_low[3];
							in_heigh = angle_heigh[3]; 
							if (input_cmd) 
								add_model(in_low,in_heigh,angle_low[3],angle_heigh[3]);
							else 
								sub_model(in_low,in_heigh,angle_low[3],angle_heigh[3]);
							in_low <= angle_low[3];
							in_heigh <= angle_heigh[3];
							send_id <= reg_id; 
							end
						8'h5:
							begin
							in_low = angle_low[4];
							in_heigh = angle_heigh[4]; 
							if (input_cmd)
								add_model(in_low,in_heigh,angle_low[4],angle_heigh[4]);
							else 
								sub_model(in_low,in_heigh,angle_low[4],angle_heigh[4]);
							in_low <= angle_low[4];
							in_heigh <= angle_heigh[4];
							send_id <= reg_id; 
							end
						8'h6:
							begin
							in_low = angle_low[5];
							in_heigh = angle_heigh[5]; 
							if (input_cmd)
								add_model(in_low,in_heigh,angle_low[5],angle_heigh[5]);
							else 
								sub_model(in_low,in_heigh,angle_low[5],angle_heigh[5]);
							in_low <= angle_low[5];
							in_heigh <= angle_heigh[5];
							send_id <= reg_id; 
							end
						8'h7://一步复位
						    begin
						        send_id <= Rst_length;
						        Rst_length <= Rst_length + 3'h1;
						        case (Rst_length)
						            3'h6:
						                begin
						                in_low <= 8'hf4;
							            in_heigh <= 8'h01;
							            angle_low[5] <= 8'hf4;
							            angle_heigh[5] <=8'h01;
							            end 
						            3'h5:
						                begin
						                in_low <= 8'hee;
							            in_heigh <= 8'h01;
							            angle_low[4] <= 8'hee;
							            angle_heigh[4] <=8'h01;
							            end 
						            3'h4:
						                begin
						                in_low <= 8'hfe;
							            in_heigh <= 8'h01;
							            angle_low[3] <= 8'hfe;
							            angle_heigh[3] <=8'h01;
							            end 
						            3'h3:
						                begin
						                in_low <= 8'he4;
							            in_heigh <= 8'h01;
							            angle_low[2] <= 8'he4;
							            angle_heigh[2] <=8'h01;
							            end 
						            3'h2:
						                begin
						                in_low <= 8'hfa;
							            in_heigh <= 8'h01;
							            angle_low[1] <= 8'hfa;
							            angle_heigh[1] <=8'h01;
							            end 
						            3'h1:
						                begin
						                reg_cal <= 8'd0;
							            end 
							        default:	
								        begin
								        in_low <= 8'h0;
								        in_heigh <= 8'h0;
								        send_id <= 8'h0;
								        end
						        endcase
						    end
						8'h8://一步放下左侧
						    begin
						        send_id <= Rst_length;
						        Rst_length <= Rst_length + 3'h1;
						        case (Rst_length)
						            3'h6:
						                begin
						                in_low <= 8'h60;
							            in_heigh <= 8'h03;
							            angle_low[5] <= 8'h60;
							            angle_heigh[5] <=8'h03;
							            end 
						            3'h5:
						                begin
						                in_low <= 8'hea;
							            in_heigh <= 8'h00;
							            angle_low[4] <= 8'hea;
							            angle_heigh[4] <=8'h00;
							            end 
						            3'h4:
						                begin
						                in_low <= 8'h66;
							            in_heigh <= 8'h02;
							            angle_low[3] <= 8'h66;
							            angle_heigh[3] <=8'h02;
							            end 
						            3'h3:
						                begin
						                in_low <= 8'hac;
							            in_heigh <= 8'h00;
							            angle_low[2] <= 8'hac;
							            angle_heigh[2] <=8'h00;
							            end 
						            3'h2:
						                begin
						                in_low <= 8'hfa;
							            in_heigh <= 8'h01;
							            angle_low[1] <= 8'hfa;
							            angle_heigh[1] <=8'h01;
							            end 
						            3'h1:
						                begin
						                reg_cal <= 8'd0;
							            end 
							        default:	
								        begin
								        in_low <= 8'h0;
								        in_heigh <= 8'h0;
								        send_id <= 8'h0;
								        end
						        endcase
						    end
						8'h9://一步放下右侧
						    begin
						        send_id <= Rst_length;
						        Rst_length <= Rst_length + 3'h1;
						        case (Rst_length)
						            3'h6:
						                begin
						                in_low <= 8'h6e;
							            in_heigh <= 8'h00;
							            angle_low[5] <= 8'h6e;
							            angle_heigh[5] <=8'h00;
							            end 
						            3'h5:
						                begin
						                in_low <= 8'h38;
							            in_heigh <= 8'h01;
							            angle_low[4] <= 8'h38;
							            angle_heigh[4] <=8'h01;
							            end 
						            3'h4:
						                begin
						                in_low <= 8'h66;
							            in_heigh <= 8'h02;
							            angle_low[3] <= 8'h66;
							            angle_heigh[3] <=8'h02;
							            end 
						            3'h3:
						                begin
						                in_low <= 8'hac;
							            in_heigh <= 8'h00;
							            angle_low[2] <= 8'hac;
							            angle_heigh[2] <=8'h00;
							            end 
						            3'h2:
						                begin
						                in_low <= 8'hfa;
							            in_heigh <= 8'h01;
							            angle_low[1] <= 8'hfa;
							            angle_heigh[1] <=8'h01;
							            end 
						            3'h1:
						                begin
						                reg_cal <= 8'd0;
							            end 
							        default:	
								        begin
								        in_low <= 8'h0;
								        in_heigh <= 8'h0;
								        send_id <= 8'h0;
								        end
						        endcase
						    end
						default:	
								begin
								in_low <= 8'h0;
								in_heigh <= 8'h0;
								send_id <= 8'h0;
								end
					endcase
					state_cal <= S2 ;
					end
				S2:
					begin
					data_out[79:72] <= fill_data; // 0101 0101
					data_out[71:64] <= fill_data;// 0101 0101
					data_out[63:56] <= send_id;//reg_id
					data_out[55:48] <= 8'h07;//8'h7
					data_out[47:40] <= 8'h01;//8'h1
					data_out[39:32] <= in_low;//in_low
					data_out[31:24] <= in_heigh;//in_heigh
					data_out[23:16] <= time_low;//time_low
					data_out[15:8] <= time_heigh;//time_heigh
					data_out[7:0] = (8'hff-(send_id+8'b00000111+8'h1+in_heigh+in_low+time_heigh+time_low));//reg_cal
					state_cal <= S3;
					send_en_out <= 1'b1;
					end
				S3:
					begin
					send_en_out <= 1'b0;
		            if (Tx_Done_flag != 1)
					    state_cal <= S3;
					else
					    begin
					    state_cal <= S0;
					    if (reg_id >= 8'h7 && Rst_length != 3'h7)
					             state_cal <= S1;
					    end
					end
				endcase
				end 
			end
			
			reg return_valid;
			//返回接受有效信号
			always @(posedge Clk or negedge Rst_n)
			begin
			if(!Rst_n)
				return_valid <= 1'b0;
			else
				begin
					if(input_id != 8'h0)
						return_valid <= 1'b1;
				else
						return_valid <= 1'b0;
				end
			end
			
			task add_model;
				input [7:0] angle_low_tr;
				input [7:0] angle_heigh_tr;
				output [7:0] a_low;
				output [7:0] a_heigh;
				begin//加法 ??????????阻塞or非阻塞
				med_angle = 8'h0;
				a_low = delta_angle_low + angle_low_tr;
				med_angle = angle_heigh_tr;
				if (a_low < angle_low_tr)
					med_angle = angle_heigh_tr + 8'h01;
				a_heigh = med_angle + delta_angle_heigh;
				med_angle = 8'h0;
				end
			endtask
			
			task sub_model;
				input [7:0] angle_low_tr;
				input [7:0] angle_heigh_tr;
				output [7:0] a_low;
				output [7:0] a_heigh;
				begin
				med_angle = 8'h0;
				if (angle_heigh_tr < delta_angle_heigh)
				begin
				  a_low = 8'h0; 
				  a_heigh = 8'h0;
				end
				else
				begin
				  if (delta_angle_low <= angle_low_tr)
				  begin
					 a_low = angle_low_tr - delta_angle_low;
					 a_heigh = angle_heigh_tr - delta_angle_heigh;
			      end
				  else 
				  begin
					 if (angle_heigh_tr == delta_angle_heigh)
					 begin
					     a_low = 8'h0; 
					     a_heigh = 8'h0;
					 end
					 else
					 begin
					     a_heigh = angle_heigh_tr - delta_angle_heigh - 8'h1;
					     a_low = ~(delta_angle_low-angle_low_tr)+8'h1;
					 end
				  end
				end
		
		   		end
			endtask 
endmodule    //arm_cal_m

Robei_prj/RobeiSimulation/Top_Arm_Motor/verilog/uart_byte_tx.v
module uart_byte_tx(
	Clk,
	Rst_n,
	data_byte,
	send_en,
	Baud_Set,
	uart_tx,
	Tx_Done,
	uart_state);

	//---Ports declearation: generated by Robei---
	input Clk;
	input Rst_n;
	input [7:0] data_byte;
	input send_en;
	input [2:0] Baud_Set;
	output uart_tx;
	output Tx_Done;
	output uart_state;

	wire Clk;
	wire Rst_n;
	wire [7:0] data_byte;
	wire send_en;
	wire [2:0] Baud_Set;
	reg uart_tx;
	reg Tx_Done;
	reg uart_state;

	//----Code starts here: integrated by Robei-----
		localparam START_BIT = 1'b0;
		localparam STOP_BIT = 1'b1; 
		
		reg bps_clk;	     //波特率时钟	
		reg [15:0]div_cnt;      //分频计数器	
		reg [15:0]bps_DR;       //分频计数最大值	
		reg [3:0]bps_cnt;      //波特率时钟计数器	
		reg [7:0]data_byte_reg;//data_byte寄存后数据
		
		always@(posedge Clk or negedge Rst_n)
		if(!Rst_n)
			uart_state <= 1'b0;
		else if(send_en)
			uart_state <= 1'b1;
		else if(bps_cnt == 4'd11)
			uart_state <= 1'b0;
		else
			uart_state <= uart_state;
		
		always@(posedge Clk or negedge Rst_n)
		if(!Rst_n)
			data_byte_reg <= 8'd0;
		else if(send_en)
			data_byte_reg <= data_byte;
		else
			data_byte_reg <= data_byte_reg;
		
		always@(posedge Clk or negedge Rst_n)
		if(!Rst_n)
			bps_DR <= 16'd5207;
		else begin
			case(Baud_Set)
				0:bps_DR <= 16'd5207;
				1:bps_DR <= 16'd2603;
				2:bps_DR <= 16'd1301;
				3:bps_DR <= 16'd867;
				4:bps_DR <= 16'd433;
				default:bps_DR <= 16'd5207;			
			endcase
		end	
		
		//counter
		always@(posedge Clk or negedge Rst_n)
		if(!Rst_n)
			div_cnt <= 16'd0;
		else if(uart_state)begin
			if(div_cnt == bps_DR)
				div_cnt <= 16'd0;
			else
				div_cnt <= div_cnt + 1'b1;
		end
		else
			div_cnt <= 16'd0;
		
		// bps_clk gen
		always@(posedge Clk or negedge Rst_n)
		if(!Rst_n)
			bps_clk <= 1'b0;
		else if(div_cnt == 16'd1)
			bps_clk <= 1'b1;
		else
			bps_clk <= 1'b0;
		
		//bps counter
		always@(posedge Clk or negedge Rst_n)
		if(!Rst_n)	
			bps_cnt <= 4'd0;
		else if(bps_cnt == 4'd11)
			bps_cnt <= 4'd0;
		else if(bps_clk)
			bps_cnt <= bps_cnt + 1'b1;
		else
			bps_cnt <= bps_cnt;
			
		always@(posedge Clk or negedge Rst_n)
		if(!Rst_n)
			Tx_Done <= 1'b0;
		else if(bps_cnt == 4'd11)
			Tx_Done <= 1'b1;
		else
			Tx_Done <= 1'b0;
			
		always@(posedge Clk or negedge Rst_n)
		if(!Rst_n)
			uart_tx <= 1'b1;
		else begin
			case(bps_cnt)
				0:uart_tx <= 1'b1;
				1:uart_tx <= START_BIT;
				2:uart_tx <= data_byte_reg[0];
				3:uart_tx <= data_byte_reg[1];
				4:uart_tx <= data_byte_reg[2];
				5:uart_tx <= data_byte_reg[3];
				6:uart_tx <= data_byte_reg[4];
				7:uart_tx <= data_byte_reg[5];
				8:uart_tx <= data_byte_reg[6];
				9:uart_tx <= data_byte_reg[7];
				10:uart_tx <= STOP_BIT;
				default:uart_tx <= 1'b1;
			endcase
		end	
	
	
	
	
	
endmodule    //uart_byte_tx

Robei_prj/RobeiSimulation/uart_data_tx/verilog/uart_data_tx.v
module uart_data_tx(
	Clk,
	Rst_n,
	data,
	send_en,
	Baud_Set,
	uart_tx,
	Tx_Done,
	uart_state);

	//---Ports declearation: generated by Robei---
	input Clk;
	input Rst_n;
	input [DATA_WIDTH - 1 : 0] data;
	input send_en;
	input [2:0] Baud_Set;
	output uart_tx;
	output Tx_Done;
	output uart_state;

	wire Clk;
	wire Rst_n;
	wire [DATA_WIDTH - 1 : 0] data;
	wire send_en;
	wire [2:0] Baud_Set;
	wire uart_tx;
	reg Tx_Done;
	wire uart_state;

	//----Code starts here: integrated by Robei-----
		parameter DATA_WIDTH = 80;
		parameter MSB_FIRST = 1;
	
		reg [DATA_WIDTH-1 : 0]data_r;         //这里得改
	
		reg [7:0] data_byte;
		reg byte_send_en;
		wire byte_tx_done;
	
		reg [8:0]cnt;
		reg [1:0]state;
		
		localparam S0 = 0;	//等待发送请求
		localparam S1 = 1;	//发起单字节数据发送
		localparam S2 = 2;	//等待单字节数据发送完成
		localparam S3 = 3;	//检查所有数据是否发送完成
		
		always@(posedge Clk or negedge Rst_n)
		if(!Rst_n)begin
			data_byte <= 0;
			byte_send_en <= 0;
			state <= S0;
			cnt <= 0;
		end
		else begin
			case(state)
				S0: 
					begin
						data_byte <= 0;
						cnt <= 0;
						Tx_Done <= 0;
						if(send_en)begin
							state <= S1;
							data_r <= data;
						end
						else begin
							state <= S0;
							data_r <= data_r;
						end
					end
				
				S1:
					begin
						byte_send_en <= 1;
						if(MSB_FIRST == 1)begin
							data_byte <= data_r[DATA_WIDTH-1:DATA_WIDTH - 8];
							data_r <= data_r << 8;
						end
						else begin
							data_byte <= data_r[7:0];
							data_r <= data_r >> 8;					
						end
						state <= S2;
					end
					
				S2:
					begin
						byte_send_en <= 0;
						if(byte_tx_done)begin
							state <= S3;
							cnt <= cnt + 9'd8;
						end
						else
							state <= S2;
					end
				
				S3:
					if(cnt >= DATA_WIDTH)begin
						state <= S0;
						cnt <= 0;
						Tx_Done <= 1;
					end
					else begin
						state <= S1;
						Tx_Done <= 0;
					end
				default:state <= S0;
			endcase	
		end
	
	
	
	//---Module instantiation---
	uart_byte_tx uart_byte_tx1(
		.Clk(Clk),
		.Rst_n(Rst_n),
		.data_byte(data_byte),
		.send_en(byte_send_en),
		.Baud_Set(Baud_Set),
		.uart_tx(uart_tx),
		.Tx_Done(byte_tx_done),
		.uart_state(uart_state));

endmodule    //uart_data_tx

Robei_prj/RobeiSimulation/Arm/verilog/Arm.v
module Arm(
	Clk,
	Rst_n,
	in_id,
	Baud_Set_in,
	uart_tx,
	Tx_Done,
	uart_state,
	in_cmd);

	//---Ports declearation: generated by Robei---
	input Clk;
	input Rst_n;
	input [7:0] in_id;
	input [2:0] Baud_Set_in;
	output uart_tx;
	output Tx_Done;
	output uart_state;
	input in_cmd;

	wire Clk;
	wire Rst_n;
	wire [7:0] in_id;
	wire [2:0] Baud_Set_in;
	wire uart_tx;
	wire Tx_Done;
	wire uart_state;
	wire in_cmd;
	wire [79:0] arm_cal_m2_data_out;
	wire arm_cal_m2_send_en_out;
	wire uart_data_tx2_Tx_Done;
	assign Tx_Done = uart_data_tx2_Tx_Done;

	//----Code starts here: integrated by Robei-----
	
	
	
	
	//---Module instantiation---
	uart_data_tx uart_data_tx2(
		.Clk(Clk),
		.Rst_n(Rst_n),
		.data(arm_cal_m2_data_out),
		.send_en(arm_cal_m2_send_en_out),
		.Baud_Set(Baud_Set_in),
		.uart_tx(uart_tx),
		.Tx_Done(uart_data_tx2_Tx_Done),
		.uart_state(uart_state));

	arm_cal_m arm_cal_m2(
		.Clk(Clk),
		.Rst_n(Rst_n),
		.input_cmd(in_cmd),
		.data_out(arm_cal_m2_data_out),
		.send_en_out(arm_cal_m2_send_en_out),
		.input_id(in_id),
		.Tx_Done_flag(uart_data_tx2_Tx_Done));

endmodule    //Arm

Robei_prj/RobeiSimulation/Arm/verilog/arm_test.v
module arm_test();

	reg Clk;
	reg Rst_n;
	reg [7:0] in_id;
	reg [2:0] Baud_Set_in;
	wire uart_tx;
	wire Tx_Done;
	wire uart_state;
	reg in_cmd;

	//----Code starts here: integrated by Robei-----
		parameter DATA_WIDTH = 80;
		parameter MSB_FIRST = 1;
	
		initial Clk = 1;
		always #10 Clk = !Clk;
		
		initial begin
			Rst_n = 0;
			in_id = 0;
			in_cmd = 0;
			Baud_Set_in = 3'd4;
			#201;
			Rst_n = 1;
			#200;
			in_id = 8'h2;
			in_cmd = 1'b1;
			Baud_Set_in = 3'd4;
			#20;
			in_id =8'b00000000;
			@(posedge Tx_Done);
			#20000;
			in_id = 8'h2;
			in_cmd = 1'b1;
			#20;
			in_id =8'b00000000;
			@(posedge Tx_Done);
			#20;
			in_id = 8'h9;
			in_cmd = 1'b0;
			#20;
			in_id =8'b00000000;
			#20000;
			in_id = 8'h2;
			in_cmd = 1'b0;
			#20;
			in_id =8'b00000000;
			@(posedge Tx_Done);
			#20;
			$finish;		
		end
	initial begin
		$dumpfile ("E:/CodeFile/Fusai/BAJIAOBAN/Top_Final/RobeiSimulation/Arm/arm_test.vcd");
		$dumpvars;
	end
	//---Module instantiation---
	Arm Arm1(
		.Clk(Clk),
		.Rst_n(Rst_n),
		.in_id(in_id),
		.Baud_Set_in(Baud_Set_in),
		.uart_tx(uart_tx),
		.Tx_Done(Tx_Done),
		.uart_state(uart_state),
		.in_cmd(in_cmd));

endmodule    //arm_test

Robei_prj/RobeiSimulation/Arm/arm_test.vcd
$date
	Sat Jul 06 01:29:36 2024
$end
$version
	Icarus Verilog
$end
$timescale
	1s
$end
$scope module arm_test $end
$var wire 1 ! uart_tx $end
$var wire 1 " uart_state $end
$var wire 1 # Tx_Done $end
$var reg 3 $ Baud_Set_in [2:0] $end
$var reg 1 % Clk $end
$var reg 1 & Rst_n $end
$var reg 1 ' in_cmd $end
$var reg 8 ( in_id [7:0] $end
$scope module Arm1 $end
$var wire 3 ) Baud_Set_in [2:0] $end
$var wire 1 % Clk $end
$var wire 1 & Rst_n $end
$var wire 1 # Tx_Done $end
$var wire 1 ' in_cmd $end
$var wire 8 * in_id [7:0] $end
$var wire 1 ! uart_tx $end
$var wire 1 " uart_state $end
$var wire 1 + uart_data_tx2_Tx_Done $end
$var wire 1 , arm_cal_m2_send_en_out $end
$var wire 80 - arm_cal_m2_data_out [79:0] $end
$scope module arm_cal_m2 $end
$var wire 1 % Clk $end
$var wire 1 & Rst_n $end
$var wire 1 ' input_cmd $end
$var wire 8 . input_id [7:0] $end
$var wire 1 + Tx_Done_flag $end
$var reg 3 / Rst_length [2:0] $end
$var reg 80 0 data_out [79:0] $end
$var reg 8 1 in_heigh [7:0] $end
$var reg 8 2 in_low [7:0] $end
$var reg 8 3 med_angle [7:0] $end
$var reg 8 4 reg_cal [7:0] $end
$var reg 8 5 reg_id [7:0] $end
$var reg 1 6 return_valid $end
$var reg 1 , send_en_out $end
$var reg 8 7 send_id [7:0] $end
$var reg 2 8 state_cal [1:0] $end
$scope task add_model $end
$var reg 8 9 a_heigh [7:0] $end
$var reg 8 : a_low [7:0] $end
$var reg 8 ; angle_heigh_tr [7:0] $end
$var reg 8 < angle_low_tr [7:0] $end
$upscope $end
$scope task sub_model $end
$var reg 8 = a_heigh [7:0] $end
$var reg 8 > a_low [7:0] $end
$var reg 8 ? angle_heigh_tr [7:0] $end
$var reg 8 @ angle_low_tr [7:0] $end
$upscope $end
$upscope $end
$scope module uart_data_tx2 $end
$var wire 3 A Baud_Set [2:0] $end
$var wire 1 % Clk $end
$var wire 1 & Rst_n $end
$var wire 80 B data [79:0] $end
$var wire 1 , send_en $end
$var wire 1 ! uart_tx $end
$var wire 1 " uart_state $end
$var wire 1 C byte_tx_done $end
$var reg 1 + Tx_Done $end
$var reg 1 D byte_send_en $end
$var reg 9 E cnt [8:0] $end
$var reg 8 F data_byte [7:0] $end
$var reg 80 G data_r [79:0] $end
$var reg 2 H state [1:0] $end
$scope module uart_byte_tx1 $end
$var wire 3 I Baud_Set [2:0] $end
$var wire 1 % Clk $end
$var wire 1 & Rst_n $end
$var wire 8 J data_byte [7:0] $end
$var wire 1 D send_en $end
$var reg 1 C Tx_Done $end
$var reg 16 K bps_DR [15:0] $end
$var reg 1 L bps_clk $end
$var reg 4 M bps_cnt [3:0] $end
$var reg 8 N data_byte_reg [7:0] $end
$var reg 16 O div_cnt [15:0] $end
$var reg 1 " uart_state $end
$var reg 1 ! uart_tx $end
$upscope $end
$upscope $end
$upscope $end
$upscope $end
$enddefinitions $end
#0
$dumpvars
b0 O
b0 N
b0 M
0L
b1010001010111 K
b0 J
b100 I
b0 H
bx G
b0 F
b0 E
0D
0C
bx B
b100 A
bx @
bx ?
bx >
bx =
bx <
bx ;
bx :
bx 9
b0 8
b0 7
06
b0 5
b0 4
b0 3
b0 2
b0 1
bx 0
b10 /
b0 .
bx -
x,
x+
b0 *
b100 )
b0 (
0'
0&
1%
b100 $
x#
0"
1!
$end
#10
0%
#20
1%
#30
0%
#40
1%
#50
0%
#60
1%
#70
0%
#80
1%
#90
0%
#100
1%
#110
0%
#120
1%
#130
0%
#140
1%
#150
0%
#160
1%
#170
0%
#180
1%
#190
0%
#200
1%
#201
1&
#210
0%
#220
0#
0+
b100100000 K
1%
#230
0%
#240
1%
#250
0%
#260
1%
#270
0%
#280
1%
#290
0%
#300
1%
#310
0%
#320
1%
#330
0%
#340
1%
#350
0%
#360
1%
#370
0%
#380
1%
#390
0%
#400
1%
#401
1'
b10 (
b10 *
b10 .
#410
0%
#420
16
b10 5
b1 8
1%
#421
b0 (
b0 *
b0 .
#430
0%
#440
b10 8
b10 7
06
b10 9
b0 3
b10100 :
b1 ;
b11111010 <
b10 1
b10100 2
1%
#450
0%
#460
1,
b11 8
b1010101010101010000001000000111000000010001010000000010111101000000000011101011 -
b1010101010101010000001000000111000000010001010000000010111101000000000011101011 0
b1010101010101010000001000000111000000010001010000000010111101000000000011101011 B
1%
#470
0%
#480
0,
b1010101010101010000001000000111000000010001010000000010111101000000000011101011 G
b1 H
1%
#490
0%
#500
b10 H
b1010101000000100000011100000001000101000000001011110100000000001110101100000000 G
b1010101 F
b1010101 J
1D
1%
#510
0%
#520
1"
b1010101 N
0D
1%
#530
0%
#540
b1 O
1%
#550
0%
#560
b10 O
1L
1%
#570
0%
#580
b1 M
0L
b11 O
1%
#590
0%
#600
b100 O
0!
1%
#610
0%
#620
b101 O
1%
#630
0%
#640
b110 O
1%
#650
0%
#660
b111 O
1%
#670
0%
#680
b1000 O
1%
#690
0%
#700
b1001 O
1%
#710
0%
#720
b1010 O
1%
#730
0%
#740
b1011 O
1%
#750
0%
#760
b1100 O
1%
#770
0%
#780
b1101 O
1%
#790
0%
#800
b1110 O
1%
#810
0%
#820
b1111 O
1%
#830
0%
#840
b10000 O
1%
#850
0%
#860
b10001 O
1%
#870
0%
#880
b10010 O
1%
#890
0%
#900
b10011 O
1%
#910
0%
#920
b10100 O
1%
#930
0%
#940
b10101 O
1%
#950
0%
#960
b10110 O
1%
#970
0%
#980
b10111 O
1%
#990
0%
#1000
b11000 O
1%
#1010
0%
#1020
b11001 O
1%
#1030
0%
#1040
b11010 O
1%
#1050
0%
#1060
b11011 O
1%
#1070
0%
#1080
b11100 O
1%
#1090
0%
#1100
b11101 O
1%
#1110
0%
#1120
b11110 O
1%
#1130
0%
#1140
b11111 O
1%
#1150
0%
#1160
b100000 O
1%
#1170
0%
#1180
b100001 O
1%
#1190
0%
#1200
b100010 O
1%
#1210
0%
#1220
b100011 O
1%
#1230
0%
#1240
b100100 O
1%
#1250
0%
#1260
b100101 O
1%
#1270
0%
#1280
b100110 O
1%
#1290
0%
#1300
b100111 O
1%
#1310
0%
#1320
b101000 O
1%
#1330
0%
#1340
b101001 O
1%
#1350
0%
#1360
b101010 O
1%
#1370
0%
#1380
b101011 O
1%
#1390
0%
#1400
b101100 O
1%
#1410
0%
#1420
b101101 O
1%
#1430
0%
#1440
b101110 O
1%
#1450
0%
#1460
b101111 O
1%
#1470
0%
#1480
b110000 O
1%
#1490
0%
#1500
b110001 O
1%
#1510
0%
#1520
b110010 O
1%
#1530
0%
#1540
b110011 O
1%
#1550
0%
#1560
b110100 O
1%
#1570
0%
#1580
b110101 O
1%
#1590
0%
#1600
b110110 O
1%
#1610
0%
#1620
b110111 O
1%
#1630
0%
#1640
b111000 O
1%
#1650
0%
#1660
b111001 O
1%
#1670
0%
#1680
b111010 O
1%
#1690
0%
#1700
b111011 O
1%
#1710
0%
#1720
b111100 O
1%
#1730
0%
#1740
b111101 O
1%
#1750
0%
#1760
b111110 O
1%
#1770
0%
#1780
b111111 O
1%
#1790
0%
#1800
b1000000 O
1%
#1810
0%
#1820
b1000001 O
1%
#1830
0%
#1840
b1000010 O
1%
#1850
0%
#1860
b1000011 O
1%
#1870
0%
#1880
b1000100 O
1%
#1890
0%
#1900
b1000101 O
1%
#1910
0%
#1920
b1000110 O
1%
#1930
0%
#1940
b1000111 O
1%
#1950
0%
#1960
b1001000 O
1%
#1970
0%
#1980
b1001001 O
1%
#1990
0%
#2000
b1001010 O
1%
#2010
0%
#2020
b1001011 O
1%
#2030
0%
#2040
b1001100 O
1%
#2050
0%
#2060
b1001101 O
1%
#2070
0%
#2080
b1001110 O
1%
#2090
0%
#2100
b1001111 O
1%
#2110
0%
#2120
b1010000 O
1%
#2130
0%
#2140
b1010001 O
1%
#2150
0%
#2160
b1010010 O
1%
#2170
0%
#2180
b1010011 O
1%
#2190
0%
#2200
b1010100 O
1%
#2210
0%
#2220
b1010101 O
1%
#2230
0%
#2240
b1010110 O
1%
#2250
0%
#2260
b1010111 O
1%
#2270
0%
#2280
b1011000 O
1%
#2290
0%
#2300
b1011001 O
1%
#2310
0%
#2320
b1011010 O
1%
#2330
0%
#2340
b1011011 O
1%
#2350
0%
#2360
b1011100 O
1%
#2370
0%
#2380
b1011101 O
1%
#2390
0%
#2400
b1011110 O
1%
#2410
0%
#2420
b1011111 O
1%
#2430
0%
#2440
b1100000 O
1%
#2450
0%
#2460
b1100001 O
1%
#2470
0%
#2480
b1100010 O
1%
#2490
0%
#2500
b1100011 O
1%
#2510
0%
#2520
b1100100 O
1%
#2530
0%
#2540
b1100101 O
1%
#2550
0%
#2560
b1100110 O
1%
#2570
0%
#2580
b1100111 O
1%
#2590
0%
#2600
b1101000 O
1%
#2610
0%
#2620
b1101001 O
1%
#2630
0%
#2640
b1101010 O
1%
#2650
0%
#2660
b1101011 O
1%
#2670
0%
#2680
b1101100 O
1%
#2690
0%
#2700
b1101101 O
1%
#2710
0%
#2720
b1101110 O
1%
#2730
0%
#2740
b1101111 O
1%
#2750
0%
#2760
b1110000 O
1%
#2770
0%
#2780
b1110001 O
1%
#2790
0%
#2800
b1110010 O
1%
#2810
0%
#2820
b1110011 O
1%
#2830
0%
#2840
b1110100 O
1%
#2850
0%
#2860
b1110101 O
1%
#2870
0%
#2880
b1110110 O
1%
#2890
0%
#2900
b1110111 O
1%
#2910
0%
#2920
b1111000 O
1%
#2930
0%
#2940
b1111001 O
1%
#2950
0%
#2960
b1111010 O
1%
#2970
0%
#2980
b1111011 O
1%
#2990
0%
#3000
b1111100 O
1%
#3010
0%
#3020
b1111101 O
1%
#3030
0%
#3040
b1111110 O
1%
#3050
0%
#3060
b1111111 O
1%
#3070
0%
#3080
b10000000 O
1%
#3090
0%
#3100
b10000001 O
1%
#3110
0%
#3120
b10000010 O
1%
#3130
0%
#3140
b10000011 O
1%
#3150
0%
#3160
b10000100 O
1%
#3170
0%
#3180
b10000101 O
1%
#3190
0%
#3200
b10000110 O
1%
#3210
0%
#3220
b10000111 O
1%
#3230
0%
#3240
b10001000 O
1%
#3250
0%
