Robei_prj/RobeiSimulation/Top/verilog/Core_of_top.v
module Core_of_top(
	Read_temp_ok,
	Temp_data,
	CSB_data,
	LM75A_EN,
	BUZZER_EN,
	Clk,
	Rst_n);

	//---Ports declearation: generated by Robei---
	input Read_temp_ok;
	input [10:0] Temp_data;
	input [15:0] CSB_data;
	output LM75A_EN;
	output BUZZER_EN;
	input Clk;
	input Rst_n;

	wire Read_temp_ok;
	wire [10:0] Temp_data;
	wire [15:0] CSB_data;
	reg LM75A_EN;
	reg BUZZER_EN;
	wire Clk;
	wire Rst_n;

	//----Code starts here: integrated by Robei-----
				localparam  Min_distance   = 14'd50;   //±¨¾¯¾àÀë
	
	
				reg [10:0] Temp_data_buffer;
				reg [15:0] CSB_data_buffer;
	
	
				always@(posedge Clk or negedge Rst_n)
				if(!Rst_n)begin
					LM75A_EN <= 0;
					BUZZER_EN <=0 ;
	/*
					LCD_EN <= 0;
					ARM_MOTOR_EN<= 0;
					CSB_EN<= 0;
	*/
				end
	
				else begin
					LM75A_EN <= 1;
	/*
					LCD_EN <= 1;
					ARM_MOTOR_EN <= 1;
					CSB_EN<= 1;
	*/
					Temp_data_buffer<=Temp_data;
					CSB_data_buffer<=CSB_data;
				end
	
	/*
				always@(posedge Clk or negedge Rst_n)    //¶ÁÈ¡ÎÂ¶ÈºÍ³¬Éù²¨
				if(Read_temp_ok)
					begin
					TFT_DISPLAY <={Temp_data_buffer,CSB_data_buffer} ;
					end
				else
					TFT_DISPLAY <={11'd0,CSB_data_buffer} ;
	*/
				always@(posedge Clk or negedge Rst_n)    //·äÃùÆ÷±¨¾¯
				if(!Rst_n)begin
	
					BUZZER_EN <=0 ;
	
	
				end
	
				else if(CSB_data_buffer<=Min_distance)
					begin
					BUZZER_EN <=1 ;
					end
				else
					BUZZER_EN <=0 ;	
	
				
	
endmodule    //Core_of_top

Robei_prj/RobeiSimulation/Core_of_top/verilog/Core_of_top_tb.v
module Core_of_top_tb();

	reg Read_temp_ok;
	reg [10:0] Temp_data;
	reg [15:0] CSB_data;
	wire LM75A_EN;
	wire BUZZER_EN;
	reg Clk;
	reg Rst_n;

	//----Code starts here: integrated by Robei-----
		always #10 Clk = ~Clk;
		
		initial begin
	        Clk = 1;
		    Rst_n = 0;
		    Read_temp_ok = 0;		
			Temp_data = 0;		
			CSB_data= 0;			
		    #200;
			Rst_n = 1;
			#200;
			Read_temp_ok = 1;		
			Temp_data = 11'd35;		
			#200;
			CSB_data = 14'd100;
			Read_temp_ok = 1;		
			Temp_data = 11'd40;	
			#200;
			CSB_data = 14'd30;
			Read_temp_ok = 1;		
			Temp_data = 11'd20;	
		
	
		    #2000;
		    $finish;
		end
	
	
	
	
	initial begin
		$dumpfile ("E:/CodeFile/Fusai/BAJIAOBAN/Top_Final/RobeiSimulation/Core_of_top/Core_of_top_tb.vcd");
		$dumpvars;
	end
	//---Module instantiation---
	Core_of_top Core_of_top1(
		.Read_temp_ok(Read_temp_ok),
		.Temp_data(Temp_data),
		.CSB_data(CSB_data),
		.LM75A_EN(LM75A_EN),
		.BUZZER_EN(BUZZER_EN),
		.Clk(Clk),
		.Rst_n(Rst_n));

endmodule    //Core_of_top_tb

Robei_prj/RobeiSimulation/Core_of_top/Core_of_top_tb.vcd
$date
	Sat Jul 06 01:27:03 2024
$end
$version
	Icarus Verilog
$end
$timescale
	1s
$end
$scope module Core_of_top_tb $end
$var wire 1 ! LM75A_EN $end
$var wire 1 " BUZZER_EN $end
$var reg 16 # CSB_data [15:0] $end
$var reg 1 $ Clk $end
$var reg 1 % Read_temp_ok $end
$var reg 1 & Rst_n $end
$var reg 11 ' Temp_data [10:0] $end
$scope module Core_of_top1 $end
$var wire 16 ( CSB_data [15:0] $end
$var wire 1 $ Clk $end
$var wire 1 % Read_temp_ok $end
$var wire 1 & Rst_n $end
$var wire 11 ) Temp_data [10:0] $end
$var reg 1 " BUZZER_EN $end
$var reg 16 * CSB_data_buffer [15:0] $end
$var reg 1 ! LM75A_EN $end
$var reg 11 + Temp_data_buffer [10:0] $end
$upscope $end
$upscope $end
$enddefinitions $end
#0
$dumpvars
bx +
bx *
b0 )
b0 (
b0 '
0&
0%
1$
b0 #
0"
0!
$end
#10
0$
#20
1$
#30
0$
#40
1$
#50
0$
#60
1$
#70
0$
#80
1$
#90
0$
#100
1$
#110
0$
#120
1$
#130
0$
#140
1$
#150
0$
#160
1$
#170
0$
#180
1$
#190
0$
#200
b0 *
b0 +
1!
1$
1&
#210
0$
#220
1"
1$
#230
0$
#240
1$
#250
0$
#260
1$
#270
0$
#280
1$
#290
0$
#300
1$
#310
0$
#320
1$
#330
0$
#340
1$
#350
0$
#360
1$
#370
0$
#380
1$
#390
0$
#400
b100011 +
1$
b100011 '
b100011 )
1%
#410
0$
#420
1$
#430
0$
#440
1$
#450
0$
#460
1$
#470
0$
#480
1$
#490
0$
#500
1$
#510
0$
#520
1$
#530
0$
#540
1$
#550
0$
#560
1$
#570
0$
#580
1$
#590
0$
#600
b1100100 *
b101000 +
1$
b101000 '
b101000 )
b1100100 #
b1100100 (
#610
0$
#620
0"
1$
#630
0$
#640
1$
#650
0$
#660
1$
#670
0$
#680
1$
#690
0$
#700
1$
#710
0$
#720
1$
#730
0$
#740
1$
#750
0$
#760
1$
#770
0$
#780
1$
#790
0$
#800
b11110 *
b10100 +
1$
b10100 '
b10100 )
b11110 #
b11110 (
#810
0$
#820
1"
1$
